AUTHORS
CHANGELOG.txt
DESCRIPTION
LICENSE
MANIFEST.in
README.rst
setup.py
django_traces.egg-info/PKG-INFO
django_traces.egg-info/SOURCES.txt
django_traces.egg-info/dependency_links.txt
django_traces.egg-info/requires.txt
django_traces.egg-info/top_level.txt
traces/__init__.py
traces/admin.py
traces/middleware.py
traces/models.py
traces/migrations/0001_initial.py
traces/migrations/0002_auto__add_field_trace_content_type__add_field_trace_object_id.py
traces/migrations/__init__.py
traces/templatetags/__init__.py
traces/templatetags/traces_tags.py
traces/tests/__init__.py
traces/tests/factories.py
traces/tests/middleware_tests.py
traces/tests/models_tests.py
traces/tests/runtests.py
traces/tests/south_settings.py
traces/tests/test_settings.py
traces/tests/traces_tags_tests.py
traces/tests/urls.py
traces/tests/test_app/__init__.py
traces/tests/test_app/admin.py
traces/tests/test_app/models.py
traces/tests/test_app/templates/400.html
traces/tests/test_app/templates/500.html
traces/tests/test_app/templates/base.html