Metadata-Version: 1.0
Name: django-traces
Version: 0.1
Summary: A reusable app to track view hits
Home-page: https://github.com/bitmazk/django-traces
Author: Tobias Lorenz
Author-email: tobias.lorenz@bitmazk.com
License: The MIT License
Keywords: django,app,reusable,traces,tracking,analytics
Platform: OS Independent
